{
	"owner_org": "2cc8e4b4-0c38-4590-a002-bd0d74002dec",
	"maintainer": "<Nobody>",
	"relationships_as_object": [],
	"private": false,
	"maintainer_email": "",
	"num_tags": 3,
	"id": "0edb935e-2d99-43b1-8ca0-c43e50e5d694",
	"metadata_created": "2015-02-04T19:09:03.330994",
	"metadata_modified": "2016-01-28T07:27:02.401156",
	"author": null,
	"author_email": null,
	"state": "active",
	"version": null,
	"license_id": "notspecified",
	"type": "dataset",
	"resources": [{
		"resource_group_id": "f19c52a0-4111-40f5-ad13-1995a449d491",
		"cache_last_updated": null,
		"revision_timestamp": "2016-01-28T07:27:02.401156",
		"webstore_last_updated": null,
		"id": "8c9ae0e6-f37e-4cd1-a639-16bc67ba814d",
		"size": null,
		"state": "active",
		"hash": "",
		"description": "events_300_rss.xml",
		"format": "XML",
		"tracking_summary": {
			"total": 3,
			"recent": 1
		},
		"mimetype_inner": null,
		"revision_id": "e678dc2b-cd85-4fa5-8869-7dfddc0cf6f3",
		"mimetype": "application\/xml",
		"cache_url": null,
		"name": "XML File",
		"created": "2015-02-04T14:09:03.448671",
		"url": "http:\/\/www.nycgovparks.org\/xml\/events_300_rss.xml",
		"webstore_url": null,
		"last_modified": null,
		"position": 0,
		"no_real_name": true,
		"resource_type": null
	}],
	"num_resources": 1,
	"tags": [{
		"vocabulary_id": null,
		"display_name": "calendar-of-special-events",
		"name": "calendar-of-special-events",
		"revision_timestamp": "2015-02-04T19:09:03.330994",
		"state": "active",
		"id": "aec0026d-a711-4675-a675-f98439fce7d9"
	},
	{
		"vocabulary_id": null,
		"display_name": "dpr",
		"name": "dpr",
		"revision_timestamp": "2015-02-04T19:09:03.330994",
		"state": "active",
		"id": "0afb2ff0-8c63-4045-ac6a-06971cb3c224"
	},
	{
		"vocabulary_id": null,
		"display_name": "nyc-parks-public-events-upcoming-14-days",
		"name": "nyc-parks-public-events-upcoming-14-days",
		"revision_timestamp": "2016-01-28T07:27:02.401156",
		"state": "active",
		"id": "0aa5e4bf-bb57-4dc1-a677-da5d5c1e72a2"
	}],
	"title": "NYC Parks Public Events \u2013 Upcoming 14 Days",
	"tracking_summary": {
		"total": 17,
		"recent": 1
	},
	"groups": [{
		"capacity": "public",
		"description": "Local Government Topic - for all datasets with state, local, county organizations",
		"created": "2015-04-06T16:22:44.896030",
		"title": "Local Government",
		"name": "local",
		"is_organization": false,
		"state": "active",
		"image_url": "",
		"revision_id": "a44b1716-9f9d-4db9-9b8e-321769eb8f69",
		"type": "group",
		"id": "ccc6c266-eee8-44bd-89aa-7cd8c4c6bf46",
		"approval_status": "approved"
	}],
	"relationships_as_subject": [],
	"revision_timestamp": "2016-01-28T07:27:02.401156",
	"name": "calendar-of-special-events-35840",
	"isopen": false,
	"url": null,
	"notes": "A listing of the next two weeks of events taking place on NYC Parks properties that are open to the public.",
	"license_title": "License Not Specified",
	"extras": [{
		"key": "publisher",
		"value": "data.cityofnewyork.us"
	},
	{
		"key": "accessLevel",
		"value": "public"
	},
	{
		"key": "catalog_describedBy",
		"value": "https:\/\/project-open-data.cio.gov\/v1.1\/schema\/catalog.json"
	},
	{
		"key": "harvest_source_id",
		"value": "50104281-92a3-4534-9d38-141bc82276c5"
	},
	{
		"key": "catalog_@context",
		"value": "https:\/\/project-open-data.cio.gov\/v1.1\/schema\/catalog.jsonld"
	},
	{
		"key": "issued",
		"value": "2011-08-11"
	},
	{
		"key": "resource-type",
		"value": "Dataset"
	},
	{
		"key": "modified",
		"value": "2015-08-05"
	},
	{
		"key": "harvest_source_title",
		"value": "NYC JSON"
	},
	{
		"key": "source_schema_version",
		"value": "1.1"
	},
	{
		"key": "source_datajson_identifier",
		"value": true
	},
	{
		"key": "theme",
		"value": ["Recreation"]
	},
	{
		"key": "catalog_@id",
		"value": "https:\/\/data.cityofnewyork.us\/data.json"
	},
	{
		"key": "catalog_conformsTo",
		"value": "https:\/\/project-open-data.cio.gov\/v1.1\/schema"
	},
	{
		"key": "identifier",
		"value": "https:\/\/data.cityofnewyork.us\/api\/views\/w3wp-dpdi"
	},
	{
		"key": "landingPage",
		"value": "https:\/\/data.cityofnewyork.us\/d\/w3wp-dpdi"
	},
	{
		"key": "harvest_object_id",
		"value": "f0d33330-1249-4136-b9a8-e7a2ac52feef"
	},
	{
		"key": "source_hash",
		"value": "64eb42f4ed2ebdfd6c65dfb4766d3797a50cb4d8"
	},
	{
		"state": "active",
		"key": "harvest_object_id",
		"value": "f0d33330-1249-4136-b9a8-e7a2ac52feef"
	},
	{
		"state": "active",
		"key": "harvest_source_id",
		"value": "50104281-92a3-4534-9d38-141bc82276c5"
	},
	{
		"state": "active",
		"key": "harvest_source_title",
		"value": "NYC JSON"
	}],
	"organization": {
		"description": "",
		"created": "2014-04-16T13:28:34.570999",
		"title": "City of New York",
		"name": "city-of-new-york",
		"revision_timestamp": "2014-04-16T17:28:34.522845",
		"is_organization": true,
		"state": "active",
		"image_url": "",
		"revision_id": "2d414259-f4eb-4403-8bec-7b6f2a01e455",
		"type": "organization",
		"id": "2cc8e4b4-0c38-4590-a002-bd0d74002dec",
		"approval_status": "approved"
	},
	"revision_id": "e678dc2b-cd85-4fa5-8869-7dfddc0cf6f3"
}