{
	"owner_org": "149dc403-f16f-4e9d-a9c9-39babf7e98bf",
	"maintainer": "Data Administrator",
	"relationships_as_object": [],
	"private": false,
	"maintainer_email": "da.mailbox@ssa.gov",
	"num_tags": 10,
	"id": "312c3d9c-e355-4c81-b127-d4d3987fdba1",
	"metadata_created": "2015-02-28T17:15:00.059392",
	"metadata_modified": "2016-10-29T19:05:31.281171",
	"author": null,
	"author_email": null,
	"state": "active",
	"version": null,
	"license_id": "us-pd",
	"type": "dataset",
	"resources": [],
	"num_resources": 0,
	"tags": [{
		"vocabulary_id": null,
		"display_name": "accounting-system",
		"name": "accounting-system",
		"revision_timestamp": "2015-02-28T17:15:00.059392",
		"state": "active",
		"id": "ca1a3e2a-7c35-4bf7-87e0-54c1426de88b"
	},
	{
		"vocabulary_id": null,
		"display_name": "accounts-payable",
		"name": "accounts-payable",
		"revision_timestamp": "2015-02-28T17:15:00.059392",
		"state": "active",
		"id": "b6da727b-bf5e-4ea3-8b1e-5ee8aaa53bc3"
	},
	{
		"vocabulary_id": null,
		"display_name": "accounts-receivable",
		"name": "accounts-receivable",
		"revision_timestamp": "2015-02-28T17:15:00.059392",
		"state": "active",
		"id": "45b49ba0-da41-49e4-93ab-d717f1f3fa2b"
	},
	{
		"vocabulary_id": null,
		"display_name": "administrative-payments",
		"name": "administrative-payments",
		"revision_timestamp": "2015-02-28T17:15:00.059392",
		"state": "active",
		"id": "49da63bd-5795-471a-9e31-850c767e2c15"
	},
	{
		"vocabulary_id": null,
		"display_name": "fis",
		"name": "fis",
		"revision_timestamp": "2015-02-28T17:15:00.059392",
		"state": "active",
		"id": "2ac10ca7-d8a7-43a3-8474-652a19da1a7f"
	},
	{
		"vocabulary_id": null,
		"display_name": "general-ledger",
		"name": "general-ledger",
		"revision_timestamp": "2015-02-28T17:15:00.059392",
		"state": "active",
		"id": "13ff8ee0-2760-44ce-883d-bdeda67fc87d"
	},
	{
		"vocabulary_id": null,
		"display_name": "obligations",
		"name": "obligations",
		"revision_timestamp": "2015-02-28T17:15:00.059392",
		"state": "active",
		"id": "bbd11b58-e484-436b-89bb-0bfc475d2dec"
	},
	{
		"vocabulary_id": null,
		"display_name": "purchasing",
		"name": "purchasing",
		"revision_timestamp": "2015-02-28T17:15:00.059392",
		"state": "active",
		"id": "031f628c-8bcb-4c6a-8d5b-6e9448324682"
	},
	{
		"vocabulary_id": null,
		"display_name": "sers",
		"name": "sers",
		"revision_timestamp": "2015-02-28T17:15:00.059392",
		"state": "active",
		"id": "2b7381c3-7581-4070-8ace-074fa5d13013"
	},
	{
		"vocabulary_id": null,
		"display_name": "ssoars",
		"name": "ssoars",
		"revision_timestamp": "2015-02-28T17:15:00.059392",
		"state": "active",
		"id": "dfb4f9c8-3c3b-4e4e-a295-4ce7ceed96c1"
	}],
	"title": "Social Security On-Line Accounting and Reporting System (SSOARS)",
	"tracking_summary": {
		"total": 56,
		"recent": 2
	},
	"groups": [],
	"relationships_as_subject": [],
	"revision_timestamp": "2016-03-19T22:24:40.154217",
	"name": "social-security-on-line-accounting-and-reporting-system-ssoars",
	"isopen": true,
	"url": null,
	"notes": "SSOARS is the official book of record accounting system for SSA. It records all financial transactions for the agency and process administrative payments and collections.",
	"license_title": "U.S. Government Work",
	"extras": [{
		"key": "publisher",
		"value": "Social Security Administration"
	},
	{
		"key": "accessLevel",
		"value": "non-public"
	},
	{
		"key": "license",
		"value": "https://www.usa.gov/publicdomain/label/1.0/"
	},
	{
		"key": "harvest_source_id",
		"value": "3ab711e9-e33a-4f1e-a524-30be635dbce0"
	},
	{
		"key": "rights",
		"value": "The publishing of the data asset cannot be done due to one or more of the following reasons: contains personal identifying information, contains federal tax information, contains sensitive information, or a data assessment has not been completed."
	},
	{
		"key": "resource-type",
		"value": "Dataset"
	},
	{
		"key": "modified",
		"value": "2016-10-28"
	},
	{
		"key": "harvest_source_title",
		"value": "SSA JSON"
	},
	{
		"key": "source_schema_version",
		"value": "1.1"
	},
	{
		"key": "source_datajson_identifier",
		"value": true
	},
	{
		"key": "programCode",
		"value": ["016:000"]
	},
	{
		"key": "bureauCode",
		"value": ["016:00"]
	},
	{
		"key": "catalog_conformsTo",
		"value": "https://project-open-data.cio.gov/v1.1/schema"
	},
	{
		"key": "identifier",
		"value": "US-GOV-SSA-406"
	},
	{
		"key": "harvest_object_id",
		"value": "f73ab838-98b0-42c0-8ce2-4aa25ed045e3"
	},
	{
		"key": "source_hash",
		"value": "14a86f43ee58dc8f1d09d235718b8e768e231f80"
	},
	{
		"key": "catalog_describedBy",
		"value": "https://project-open-data.cio.gov/v1.1/schema/catalog.json"
	},
	{
		"state": "active",
		"key": "harvest_object_id",
		"value": "f73ab838-98b0-42c0-8ce2-4aa25ed045e3"
	},
	{
		"state": "active",
		"key": "harvest_source_id",
		"value": "3ab711e9-e33a-4f1e-a524-30be635dbce0"
	},
	{
		"state": "active",
		"key": "harvest_source_title",
		"value": "SSA JSON"
	}],
	"license_url": "http://www.usa.gov/publicdomain/label/1.0/",
	"organization": {
		"description": "",
		"created": "2013-05-18T11:35:25.934290",
		"title": "Social Security Administration",
		"name": "ssa-gov",
		"revision_timestamp": "2015-02-25T20:32:33.216893",
		"is_organization": true,
		"state": "active",
		"image_url": "https://raw.githubusercontent.com/GSA/logo/master/ssa.png",
		"revision_id": "1be01963-921d-432f-b56d-37fa76dfb0a1",
		"type": "organization",
		"id": "149dc403-f16f-4e9d-a9c9-39babf7e98bf",
		"approval_status": "approved"
	},
	"revision_id": "befa68de-bdc8-487e-b06d-0041cbf763d3"
}