{
	"owner_org": "4d7ad1cd-3641-420b-8116-e4082f49cd44",
	"maintainer": "Richard Easterbrook",
	"relationships_as_object": [],
	"private": false,
	"maintainer_email": "richard_easterbrook@fws.gov",
	"num_tags": 7,
	"id": "705263b3-cd0d-48e1-a629-0695c370c00b",
	"metadata_created": "2014-04-24T14:43:18.262060",
	"metadata_modified": "2016-07-27T22:21:53.413393",
	"author": null,
	"author_email": null,
	"state": "active",
	"version": null,
	"license_id": "notspecified",
	"type": "dataset",
	"resources": [{
		"resource_group_id": "ed9cb9fa-cc19-4c06-a94f-dd34dd9c9bd5",
		"cache_last_updated": null,
		"revision_timestamp": "2016-07-27T22:21:53.413393",
		"webstore_last_updated": null,
		"id": "8ea99576-40f9-457c-9f34-1b3260bb6b9f",
		"size": null,
		"state": "active",
		"hash": "",
		"description": "PDF",
		"format": "PDF",
		"tracking_summary": {
			"total": 0,
			"recent": 0
		},
		"mimetype_inner": null,
		"mimetype": "application/pdf",
		"cache_url": null,
		"name": "SHB_1986_USFWS_ManagementPlan.pdf",
		"created": "2016-07-27T18:21:53.531564",
		"url": "https://ecos.fws.gov/ServCat/DownloadFile/3370?Reference=3517",
		"webstore_url": null,
		"last_modified": null,
		"position": 0,
		"revision_id": "00e361e0-f997-4350-9ac1-1c2a1df2fbbf",
		"resource_type": null
	}],
	"num_resources": 1,
	"tags": [{
		"vocabulary_id": null,
		"display_name": "grassland",
		"name": "grassland",
		"revision_timestamp": "2014-04-24T14:43:18.262060",
		"state": "active",
		"id": "d0bb1d00-4474-471f-9b12-3096aecd2c96"
	},
	{
		"vocabulary_id": null,
		"display_name": "habitat",
		"name": "habitat",
		"revision_timestamp": "2014-04-24T14:43:18.262060",
		"state": "active",
		"id": "0d8d4453-7326-4c6a-b2ac-6ae80e8ca834"
	},
	{
		"vocabulary_id": null,
		"display_name": "recreation",
		"name": "recreation",
		"revision_timestamp": "2014-04-24T14:43:18.262060",
		"state": "active",
		"id": "6041d0a4-2634-4ea3-bad4-6b73cffe0e25"
	},
	{
		"vocabulary_id": null,
		"display_name": "waterfowl",
		"name": "waterfowl",
		"revision_timestamp": "2014-04-24T14:43:18.262060",
		"state": "active",
		"id": "1fd404ba-b105-456c-8441-2ba3aa07b0d2"
	},
	{
		"vocabulary_id": null,
		"display_name": "wetland",
		"name": "wetland",
		"revision_timestamp": "2014-04-24T14:43:18.262060",
		"state": "active",
		"id": "1455ec7b-a599-4b16-9850-9c9a39b986ce"
	},
	{
		"vocabulary_id": null,
		"display_name": "wildlife",
		"name": "wildlife",
		"revision_timestamp": "2014-04-24T14:43:18.262060",
		"state": "active",
		"id": "a7724339-a6a5-4c27-8611-ecfeff2ad725"
	},
	{
		"vocabulary_id": null,
		"display_name": "woodland",
		"name": "woodland",
		"revision_timestamp": "2014-04-24T14:43:18.262060",
		"state": "active",
		"id": "7a8b7a44-4f44-472e-9b21-521afd79ac3a"
	}],
	"title": "Management Plan Parts I and II: Sherburne National Wildlife Refuge",
	"tracking_summary": {
		"total": 2,
		"recent": 1
	},
	"groups": [],
	"relationships_as_subject": [],
	"revision_timestamp": "2014-04-24T14:43:18.262060",
	"name": "management-plan-parts-i-and-ii-sherburne-national-wildlife-refuge",
	"isopen": false,
	"url": null,
	"notes": "This plan provides information on the background, objectives and management strategy for Sherburne National Wildlife Refuge.",
	"license_title": "License Not Specified",
	"extras": [{
		"key": "harvest_source_id",
		"value": "269d76fb-fa7e-49d2-a6bb-3a9e3f1bee70"
	},
	{
		"key": "issued",
		"value": "1986-12-02"
	},
	{
		"key": "resource-type",
		"value": "Dataset"
	},
	{
		"key": "references",
		"value": ["https://ecos.fws.gov/ServCat/Reference/Profile/3517"]
	},
	{
		"key": "source_hash",
		"value": "cb1edc3a43a2dc2ff6e22a2a007ffac56d1983cf"
	},
	{
		"key": "accessLevel",
		"value": "public"
	},
	{
		"key": "theme",
		"value": ["Plan"]
	},
	{
		"key": "spatial",
		"value": "-93.84557,45.4042,-93.63082,45.5412064"
	},
	{
		"key": "catalog_conformsTo",
		"value": "https://project-open-data.cio.gov/v1.1/schema"
	},
	{
		"key": "catalog_@context",
		"value": "https://project-open-data.cio.gov/v1.1/schema/catalog.jsonld"
	},
	{
		"key": "catalog_describedBy",
		"value": "https://project-open-data.cio.gov/v1.1/schema/catalog.json"
	},
	{
		"key": "harvest_source_title",
		"value": "fwsjson"
	},
	{
		"key": "source_schema_version",
		"value": "1.1"
	},
	{
		"key": "programCode",
		"value": ["010:094",
		"010:028"]
	},
	{
		"key": "bureauCode",
		"value": ["010:18"]
	},
	{
		"key": "landingPage",
		"value": "https://ecos.fws.gov/ServCat/Reference/Profile/3517"
	},
	{
		"key": "harvest_object_id",
		"value": "afbea5b2-c082-493d-8312-5a8fc816fcf9"
	},
	{
		"key": "publisher",
		"value": "Fish and Wildlife Service"
	},
	{
		"key": "modified",
		"value": "1986-12-02"
	},
	{
		"key": "source_datajson_identifier",
		"value": true
	},
	{
		"key": "catalog_@id",
		"value": "C:\Program Files (x86)\FWS\DataStore\Application\OpenData\FWS_ServCat_v1_1.json"
	},
	{
		"key": "dataQuality",
		"value": true
	},
	{
		"key": "identifier",
		"value": "FWS_ServCat_3517"
	},
	{
		"state": "active",
		"key": "harvest_object_id",
		"value": "afbea5b2-c082-493d-8312-5a8fc816fcf9"
	},
	{
		"state": "active",
		"key": "harvest_source_id",
		"value": "269d76fb-fa7e-49d2-a6bb-3a9e3f1bee70"
	},
	{
		"state": "active",
		"key": "harvest_source_title",
		"value": "fwsjson"
	}],
	"organization": {
		"description": "",
		"created": "2013-03-14T03:44:48.890979",
		"title": "US Fish and Wildlife Service, Department of the Interior",
		"name": "fws-gov",
		"revision_timestamp": "2013-08-10T21:40:21.503248",
		"is_organization": true,
		"state": "active",
		"image_url": "http://upload.wikimedia.org/wikipedia/commons/0/0c/US-FishAndWildlifeService-Logo.svg",
		"revision_id": "353573b3-02ba-4e95-a876-828e8972ac08",
		"type": "organization",
		"id": "4d7ad1cd-3641-420b-8116-e4082f49cd44",
		"approval_status": "approved"
	},
	"revision_id": "3e663364-4add-47a0-81cb-8d1f70a5c64e"
}