{
	"owner_org": "4d7ad1cd-3641-420b-8116-e4082f49cd44",
	"maintainer": "Richard Easterbrook",
	"relationships_as_object": [],
	"private": false,
	"maintainer_email": "richard_easterbrook@fws.gov",
	"num_tags": 7,
	"id": "738e2b7f-031f-46f9-9130-74e8ecb10ef5",
	"metadata_created": "2014-04-24T15:03:40.028190",
	"metadata_modified": "2016-07-27T22:42:14.569001",
	"author": null,
	"author_email": null,
	"state": "active",
	"version": null,
	"license_id": "notspecified",
	"type": "dataset",
	"resources": [{
		"resource_group_id": "e00b31d6-a5bc-4017-83c8-1b39f1475e69",
		"cache_last_updated": null,
		"revision_timestamp": "2016-07-27T22:42:14.569001",
		"webstore_last_updated": null,
		"id": "056eb949-a390-4f04-9ffa-23cf489e37da",
		"size": null,
		"state": "active",
		"hash": "",
		"description": "",
		"format": "PDF",
		"tracking_summary": {
			"total": 0,
			"recent": 0
		},
		"mimetype_inner": null,
		"mimetype": "application\/pdf",
		"cache_url": null,
		"name": "5N25.pdf",
		"created": "2016-07-27T18:42:14.646501",
		"url": "https:\/\/ecos.fws.gov\/ServCat\/DownloadFile\/21815?Reference=23296",
		"webstore_url": null,
		"last_modified": null,
		"position": 0,
		"revision_id": "ae1239fe-f516-41b2-8d7d-6113a21f4304",
		"resource_type": null
	}],
	"num_resources": 1,
	"tags": [{
		"vocabulary_id": null,
		"display_name": "birds",
		"name": "birds",
		"revision_timestamp": "2014-04-24T15:03:40.028190",
		"state": "active",
		"id": "52b10bb7-3253-4a45-9c2f-7c4684eba63a"
	},
	{
		"vocabulary_id": null,
		"display_name": "egg",
		"name": "egg",
		"revision_timestamp": "2014-04-24T15:03:40.028190",
		"state": "active",
		"id": "d8f6fd47-9bee-4b9d-86d9-5feceee97a19"
	},
	{
		"vocabulary_id": null,
		"display_name": "environmental-contaminants-investigation",
		"name": "environmental-contaminants-investigation",
		"revision_timestamp": "2014-04-24T15:03:40.028190",
		"state": "active",
		"id": "b663e08c-c150-4e00-8149-8b3a35c0787f"
	},
	{
		"vocabulary_id": null,
		"display_name": "fledglings",
		"name": "fledglings",
		"revision_timestamp": "2014-04-24T15:03:40.028190",
		"state": "active",
		"id": "8ca48b85-ed6d-45d5-9748-8418cbe2cf89"
	},
	{
		"vocabulary_id": null,
		"display_name": "hatchlings",
		"name": "hatchlings",
		"revision_timestamp": "2014-04-24T15:03:40.028190",
		"state": "active",
		"id": "8b9a9e78-6a54-4355-9d0f-976b3490f48d"
	},
	{
		"vocabulary_id": null,
		"display_name": "monitoring-plan-for-the-american-peregrine-falcon",
		"name": "monitoring-plan-for-the-american-peregrine-falcon",
		"revision_timestamp": "2014-04-24T15:03:40.028190",
		"state": "active",
		"id": "4fc0c354-46f2-41bb-aa2b-4042f40cac7d"
	},
	{
		"vocabulary_id": null,
		"display_name": "nesting",
		"name": "nesting",
		"revision_timestamp": "2014-04-24T15:03:40.028190",
		"state": "active",
		"id": "7aaf5e47-2e4e-4b86-8002-3bd8bb692962"
	}],
	"title": "Organochlorine pesticides, PCBs, dioxins and metals in post-term peregrine falcon (Falco peregrinus) eggs from the mid-Atlantic states: New Jersey, Pennsylvania, Delaware, Maryland, and Virginia: 1993-1999",
	"tracking_summary": {
		"total": 14,
		"recent": 0
	},
	"groups": [],
	"relationships_as_subject": [],
	"revision_timestamp": "2016-07-27T22:42:14.569001",
	"name": "organochlorine-pesticides-pcbs-dioxins-and-metals-in-post-term-peregrine-falcon-falco-1993",
	"isopen": false,
	"url": null,
	"notes": "For Peregrine falcons represented by post-term egg residues in this study, eggshell thicknesses (n = 93) were not at levels known to be critical for effects to next success. There was no statistically significant effect of contaminants on next success (n, clutches =73). DDE remained negatively correlated with thickness. Residues of persistent organochlorines, PCBs and metals were detected in these post-term eggs; some residues approach critical levels for effects to birds. Enacting a sampling plan of the breeding population for the Mid-Western\/Northeastern Recovery Region, as described in the Monitoring Plan for the American Peregrine Falcon (USFWS 2003), is advisable. Promoting peregrine falcon nesting in the historic inland habitat in the coastal states is advisable as the coastal nesters appear to bear higher contaminant burdens than those peregrine falcons that forage inland or on more resident prey populations. The coastal nesting peregrines may be accumulating contaminants at higher levels than inland nesting birds due to the somewhat more migrant coastal prey base that may be exposed to bioaccumulative contaminants in many locations. Implementing a randomized egg sampling regime, in accordance with provisions in the Monitoring Plan, would encompass the entire recovery region population and include greater representation from peregrines nesting in more historic habitat. Comprehensive records on number of eggs laid, hatchlings and fledglings at banding would facilitate a more detailed analysis of contaminant effects on productivity as number of nestlings, rather than as successful (>1 chicks at banding) or unsuccessful (0 chicks at banding) nesting. Tracking banded female productivity over a number of years, analyzing eggs on a periodic basis, and tracking winter migration routes and areas of females, although many peregrines falcons in this region are non-migratory, would also allow examination of contaminant trends over time and perhaps discern effects due to foraging and environmental factors.",
	"license_title": "License Not Specified",
	"extras": [{
		"key": "harvest_source_id",
		"value": "269d76fb-fa7e-49d2-a6bb-3a9e3f1bee70"
	},
	{
		"key": "issued",
		"value": "2004-01-01"
	},
	{
		"key": "resource-type",
		"value": "Dataset"
	},
	{
		"key": "references",
		"value": ["https:\/\/ecos.fws.gov\/ServCat\/Reference\/Profile\/23296"]
	},
	{
		"key": "source_hash",
		"value": "35d5aaf5aa4f5e49f3fb42757b97babc574cd4aa"
	},
	{
		"key": "accessLevel",
		"value": "public"
	},
	{
		"key": "theme",
		"value": ["Unpublished Report"]
	},
	{
		"key": "spatial",
		"value": "-81.38281,36.4798431,-73.50195,42.03265"
	},
	{
		"key": "catalog_conformsTo",
		"value": "https:\/\/project-open-data.cio.gov\/v1.1\/schema"
	},
	{
		"key": "catalog_@context",
		"value": "https:\/\/project-open-data.cio.gov\/v1.1\/schema\/catalog.jsonld"
	},
	{
		"key": "catalog_describedBy",
		"value": "https:\/\/project-open-data.cio.gov\/v1.1\/schema\/catalog.json"
	},
	{
		"key": "harvest_source_title",
		"value": "fwsjson"
	},
	{
		"key": "source_schema_version",
		"value": "1.1"
	},
	{
		"key": "programCode",
		"value": ["010:094",
		"010:028"]
	},
	{
		"key": "bureauCode",
		"value": ["010:18"]
	},
	{
		"key": "landingPage",
		"value": "https:\/\/ecos.fws.gov\/ServCat\/Reference\/Profile\/23296"
	},
	{
		"key": "harvest_object_id",
		"value": "45d56105-d48e-44c8-8118-56a00d78ef0d"
	},
	{
		"key": "publisher",
		"value": "Fish and Wildlife Service"
	},
	{
		"key": "modified",
		"value": "2004-01-01"
	},
	{
		"key": "source_datajson_identifier",
		"value": true
	},
	{
		"key": "catalog_@id",
		"value": "C:\\Program Files (x86)\\FWS\\DataStore\\Application\\OpenData\\FWS_ServCat_v1_1.json"
	},
	{
		"key": "dataQuality",
		"value": true
	},
	{
		"key": "identifier",
		"value": "FWS_ServCat_23296"
	},
	{
		"state": "active",
		"key": "harvest_object_id",
		"value": "45d56105-d48e-44c8-8118-56a00d78ef0d"
	},
	{
		"state": "active",
		"key": "harvest_source_id",
		"value": "269d76fb-fa7e-49d2-a6bb-3a9e3f1bee70"
	},
	{
		"state": "active",
		"key": "harvest_source_title",
		"value": "fwsjson"
	}],
	"organization": {
		"description": "",
		"created": "2013-03-14T03:44:48.890979",
		"title": "US Fish and Wildlife Service, Department of the Interior",
		"name": "fws-gov",
		"revision_timestamp": "2013-08-10T21:40:21.503248",
		"is_organization": true,
		"state": "active",
		"image_url": "http:\/\/upload.wikimedia.org\/wikipedia\/commons\/0\/0c\/US-FishAndWildlifeService-Logo.svg",
		"revision_id": "353573b3-02ba-4e95-a876-828e8972ac08",
		"type": "organization",
		"id": "4d7ad1cd-3641-420b-8116-e4082f49cd44",
		"approval_status": "approved"
	},
	"revision_id": "ae1239fe-f516-41b2-8d7d-6113a21f4304"
}