{
	"owner_org": "ff9ae098-eccc-41d8-bfcd-5e8ed047db05",
	"maintainer": "Tom Garin",
	"relationships_as_object": [],
	"private": false,
	"maintainer_email": "Tom.Garin@va.gov",
	"num_tags": 1,
	"id": "86506f83-ae10-4d1a-9072-8478940bed90",
	"metadata_created": "2015-10-29T08:27:27.561146",
	"metadata_modified": "2015-10-29T08:27:27.561146",
	"author": null,
	"author_email": null,
	"state": "active",
	"version": null,
	"license_id": "cc-zero",
	"type": "dataset",
	"resources": [{
		"resource_group_id": "e014e863-77cc-4636-bd70-097d9d6eb82b",
		"cache_last_updated": null,
		"revision_timestamp": "2015-10-29T08:27:27.561146",
		"webstore_last_updated": null,
		"id": "be776fe1-c798-49a7-8f7a-a008acdd9e2a",
		"size": null,
		"state": "active",
		"hash": "",
		"description": "This summaries the services and programs VA provided in Arizona in fiscal year 2014.",
		"format": "PDF",
		"tracking_summary": {
			"total": 1,
			"recent": 1
		},
		"mimetype_inner": null,
		"mimetype": "application\/pdf",
		"cache_url": null,
		"name": "State Summary:  Arizona",
		"created": "2015-10-29T04:27:27.738779",
		"url": "http:\/\/www.va.gov\/vetdata\/docs\/SpecialReports\/State_Summaries_Arizona.pdf",
		"webstore_url": null,
		"last_modified": null,
		"position": 0,
		"revision_id": "f2ad2461-ca38-4b3f-8f04-d12d644d75c3",
		"resource_type": null
	}],
	"num_resources": 1,
	"tags": [{
		"vocabulary_id": null,
		"display_name": "veterans",
		"name": "veterans",
		"revision_timestamp": "2015-10-29T08:27:27.561146",
		"state": "active",
		"id": "51a40d1d-3a06-4244-a9c2-b69bec991a74"
	}],
	"title": "State Summary:  Arizona",
	"tracking_summary": {
		"total": 11,
		"recent": 1
	},
	"groups": [],
	"relationships_as_subject": [],
	"revision_timestamp": "2015-10-29T08:27:27.561146",
	"name": "state-summary-arizona",
	"isopen": true,
	"url": null,
	"notes": "This summary describes the programs and services VA provided in Arizona in fiscal year 2014.",
	"license_title": "Creative Commons CCZero",
	"extras": [{
		"key": "publisher",
		"value": "Department of Veterans Affairs"
	},
	{
		"key": "identifier",
		"value": "VA-OPP-OPP-088"
	},
	{
		"key": "license",
		"value": "http:\/\/creativecommons.org\/publicdomain\/zero\/1.0\/"
	},
	{
		"key": "harvest_source_id",
		"value": "e868f753-9395-4666-a30c-219334a64c6b"
	},
	{
		"key": "catalog_@context",
		"value": "https:\/\/project-open-data.cio.gov\/v1.1\/schema\/catalog.jsonld"
	},
	{
		"key": "resource-type",
		"value": "Dataset"
	},
	{
		"key": "modified",
		"value": "2015-10-07"
	},
	{
		"key": "harvest_source_title",
		"value": "VA JSON"
	},
	{
		"key": "source_schema_version",
		"value": "1.1"
	},
	{
		"key": "source_datajson_identifier",
		"value": true
	},
	{
		"key": "language",
		"value": ["us-EN"]
	},
	{
		"key": "bureauCode",
		"value": ["029:00"]
	},
	{
		"key": "programCode",
		"value": ["029:086"]
	},
	{
		"key": "accessLevel",
		"value": "public"
	},
	{
		"key": "harvest_object_id",
		"value": "94bd5b73-6cf3-49a7-ab85-5dfa40c0e856"
	},
	{
		"key": "source_hash",
		"value": "8e8e179f1cda1ced03a814b3856d84b2a032b34a"
	},
	{
		"key": "catalog_conformsTo",
		"value": "https:\/\/project-open-data.cio.gov\/v1.1\/schema"
	},
	{
		"key": "catalog_describedBy",
		"value": "https:\/\/project-open-data.cio.gov\/v1.1\/schema\/catalog.json"
	},
	{
		"state": "active",
		"key": "harvest_object_id",
		"value": "94bd5b73-6cf3-49a7-ab85-5dfa40c0e856"
	},
	{
		"state": "active",
		"key": "harvest_source_id",
		"value": "e868f753-9395-4666-a30c-219334a64c6b"
	},
	{
		"state": "active",
		"key": "harvest_source_title",
		"value": "VA JSON"
	}],
	"license_url": "http:\/\/www.opendefinition.org\/licenses\/cc-zero",
	"organization": {
		"description": "",
		"created": "2013-05-18T11:31:11.529883",
		"title": "Department of Veterans Affairs",
		"name": "va-gov",
		"revision_timestamp": "2014-11-19T19:55:14.636069",
		"is_organization": true,
		"state": "active",
		"image_url": "https:\/\/raw.githubusercontent.com\/GSA\/logo\/master\/va.png",
		"revision_id": "7c651ccc-eb67-439e-82dd-1ae7fff33f63",
		"type": "organization",
		"id": "ff9ae098-eccc-41d8-bfcd-5e8ed047db05",
		"approval_status": "approved"
	},
	"revision_id": "f2ad2461-ca38-4b3f-8f04-d12d644d75c3"
}