{
	"owner_org": "fc5cb2c1-d0b0-482a-8a52-7d42ea186ae1",
	"maintainer": "Mojdeh Supola",
	"relationships_as_object": [],
	"private": false,
	"maintainer_email": "Mojdeh.Supola@faa.gov",
	"num_tags": 7,
	"id": "be54fdbf-b074-4a9b-ba93-904a06f8ac1d",
	"metadata_created": "2016-05-25T00:52:46.500830",
	"metadata_modified": "2016-09-08T06:26:18.504519",
	"author": null,
	"author_email": null,
	"state": "active",
	"version": null,
	"license_id": "other-license-specified",
	"type": "dataset",
	"resources": [],
	"num_resources": 0,
	"tags": [{
		"vocabulary_id": null,
		"display_name": "airport",
		"name": "airport",
		"revision_timestamp": "2016-05-25T00:52:46.500830",
		"state": "active",
		"id": "25f02702-9d8d-4335-a9b0-366fa5cdce04"
	},
	{
		"vocabulary_id": null,
		"display_name": "airspace",
		"name": "airspace",
		"revision_timestamp": "2016-05-25T00:52:46.500830",
		"state": "active",
		"id": "653cdfbf-28dd-4cdb-ad98-3acbcf9989ec"
	},
	{
		"vocabulary_id": null,
		"display_name": "flight",
		"name": "flight",
		"revision_timestamp": "2016-05-25T00:52:46.500830",
		"state": "active",
		"id": "4338d180-5110-4c04-a24e-7c877ec88f44"
	},
	{
		"vocabulary_id": null,
		"display_name": "maintenance",
		"name": "maintenance",
		"revision_timestamp": "2016-05-25T00:52:46.500830",
		"state": "active",
		"id": "27eebc81-61c7-4e59-b75c-12ebb3c7c1ac"
	},
	{
		"vocabulary_id": null,
		"display_name": "navigation",
		"name": "navigation",
		"revision_timestamp": "2016-05-25T00:52:46.500830",
		"state": "active",
		"id": "8a1543f5-ff44-4be2-b333-38e6bbfda19d"
	},
	{
		"vocabulary_id": null,
		"display_name": "notams",
		"name": "notams",
		"revision_timestamp": "2016-05-25T00:52:46.500830",
		"state": "active",
		"id": "ac2467bb-c6c0-489e-851f-0f74395281b0"
	},
	{
		"vocabulary_id": null,
		"display_name": "procedures",
		"name": "procedures",
		"revision_timestamp": "2016-05-25T00:52:46.500830",
		"state": "active",
		"id": "938a09e7-49a0-4ddf-915a-f0a1a5eb4d71"
	}],
	"title": "Instrument Flight Procedures Automation",
	"tracking_summary": {
		"total": 11,
		"recent": 4
	},
	"groups": [],
	"relationships_as_subject": [],
	"revision_timestamp": "2016-05-25T00:52:46.500830",
	"name": "instrument-flight-procedures-automation",
	"isopen": true,
	"url": null,
	"notes": "Instrument Flight Procedures Automation (IFPA) is an automation system used to create new Instrument Flight Procedures (IFPs) and to maintain existing IFPs.IFPs provide pilots with approach paths clear of obstacles such as cell towers, buildings and trees into and out of an airport.  Procedures define the operational rules for executing defined maneuvers.  Procedure information includes approaches, holding, departures, arrivals, routes and minimum altitudes.  Procedures are developed to dictate the execution of certain National Airspace System (NAS) operations under specified conditions or avionics equipage use in the cockpit.  Effective procedures management requires periodic procedure reviews due to the impact of obstacles.  Short-term notices to pilots called Notices-to-Airmen (NOTAMs) are also developed and issued.IFPA is comprised of four key components, each with functional sub-components called modules, some of which are operational already.",
	"license_title": "Other License Specified",
	"extras": [{
		"key": "confidentiality",
		"value": false
	},
	{
		"key": "harvest_source_id",
		"value": "a400d398-0d24-4940-b8b3-6573a1670b01"
	},
	{
		"key": "issued",
		"value": "2014-11-21"
	},
	{
		"key": "resource-type",
		"value": "Dataset"
	},
	{
		"key": "systemOfRecords",
		"value": "This data requires review prior to Open Data publication."
	},
	{
		"key": "category",
		"value": "Raw data"
	},
	{
		"key": "source_hash",
		"value": "1695c840041d9db889c8fac97793305ac82ba17f"
	},
	{
		"key": "QualityResponsibleAgency",
		"value": "Federal Aviation Administration"
	},
	{
		"key": "theme",
		"value": ["Transportation"]
	},
	{
		"key": "programCode",
		"value": ["021:001"]
	},
	{
		"key": "catalog_conformsTo",
		"value": "https://project-open-data.cio.gov/v1.1/schema"
	},
	{
		"key": "subagency",
		"value": "Federal Aviation Administration"
	},
	{
		"key": "catalog_@context",
		"value": "https://project-open-data.cio.gov/v1.1/schema/catalog.jsonld"
	},
	{
		"key": "catalog_describedBy",
		"value": "https://project-open-data.cio.gov/v1.1/schema/catalog.json"
	},
	{
		"key": "collectionMode",
		"value": "Electronic"
	},
	{
		"key": "harvest_source_title",
		"value": "DOT JSON"
	},
	{
		"key": "source_schema_version",
		"value": "1.1"
	},
	{
		"key": "phone",
		"value": "202-267-1026"
	},
	{
		"key": "bureauCode",
		"value": ["021:12"]
	},
	{
		"key": "accessLevel",
		"value": "non-public"
	},
	{
		"key": "harvest_object_id",
		"value": "ae57eb4c-b45b-479d-ac2e-5231360240a2"
	},
	{
		"key": "publisher",
		"value": "Federal Aviation Administration"
	},
	{
		"key": "organizationName",
		"value": "Department of Transportation / Federal Aviation Administration"
	},
	{
		"key": "license",
		"value": "https://project-open-data.cio.gov/unknown-license/"
	},
	{
		"key": "language",
		"value": ["en-US"]
	},
	{
		"key": "rights",
		"value": "This data requires review prior to Open Data publication."
	},
	{
		"key": "publisher_hierarchy",
		"value": "U.S. Government > Department of Transportation > Federal Aviation Administration"
	},
	{
		"key": "guidelineCompliance",
		"value": false
	},
	{
		"key": "modified",
		"value": "2015-02-25"
	},
	{
		"key": "source_datajson_identifier",
		"value": true
	},
	{
		"key": "catalog_@id",
		"value": "https://www.dot.gov/data.json"
	},
	{
		"key": "categoryDesignation",
		"value": "Research"
	},
	{
		"key": "accrualPeriodicity",
		"value": "R/P1D"
	},
	{
		"key": "numberOfDatasets",
		"value": 1
	},
	{
		"key": "additionalMetadata",
		"value": "N/A"
	},
	{
		"key": "identifier",
		"value": "1745.0"
	},
	{
		"state": "active",
		"key": "harvest_object_id",
		"value": "ae57eb4c-b45b-479d-ac2e-5231360240a2"
	},
	{
		"state": "active",
		"key": "harvest_source_id",
		"value": "a400d398-0d24-4940-b8b3-6573a1670b01"
	},
	{
		"state": "active",
		"key": "harvest_source_title",
		"value": "DOT JSON"
	}],
	"organization": {
		"description": "",
		"created": "2013-05-18T11:46:56.521190",
		"title": "Department of Transportation",
		"name": "dot-gov",
		"revision_timestamp": "2013-08-30T13:59:29.523214",
		"is_organization": true,
		"state": "active",
		"image_url": "http://upload.wikimedia.org/wikipedia/commons/8/81/US_DOT_Triskelion.png",
		"revision_id": "684c8481-4ae2-46b0-a083-b392eea15130",
		"type": "organization",
		"id": "fc5cb2c1-d0b0-482a-8a52-7d42ea186ae1",
		"approval_status": "approved"
	},
	"revision_id": "0b9d91fc-4ea8-43b7-b65d-f7e23c4a5d40"
}