{
	"owner_org": "4d7ad1cd-3641-420b-8116-e4082f49cd44",
	"maintainer": "Richard Easterbrook",
	"relationships_as_object": [],
	"private": false,
	"maintainer_email": "richard_easterbrook@fws.gov",
	"num_tags": 11,
	"id": "2e16b848-4d70-470d-ac9e-f6f3dbfac2dc",
	"metadata_created": "2016-01-29T15:23:53.522464",
	"metadata_modified": "2016-11-16T19:48:02.953063",
	"author": null,
	"author_email": null,
	"state": "active",
	"version": null,
	"license_id": "notspecified",
	"type": "dataset",
	"resources": [{
		"resource_group_id": "007e0909-1a98-4886-9fbb-06b25b338f30",
		"cache_last_updated": null,
		"revision_timestamp": "2016-07-27T23:05:27.056513",
		"webstore_last_updated": null,
		"id": "4baaca14-b7a4-4ea1-9b8f-d7c06ed97a99",
		"size": null,
		"state": "active",
		"hash": "",
		"description": "",
		"format": "PDF",
		"tracking_summary": {
			"total": 0,
			"recent": 0
		},
		"mimetype_inner": null,
		"mimetype": "application\/pdf",
		"cache_url": null,
		"name": "FTN_VLT_1993_BullsnakeControl.pdf",
		"created": "2016-07-27T19:05:27.200165",
		"url": "https:\/\/ecos.fws.gov\/ServCat\/DownloadFile\/56215?Reference=55470",
		"webstore_url": null,
		"last_modified": null,
		"position": 0,
		"revision_id": "9e285a13-70f8-4719-9bda-779a98e36c64",
		"resource_type": null
	}],
	"num_resources": 1,
	"tags": [{
		"vocabulary_id": null,
		"display_name": "american-burying-beetle",
		"name": "american-burying-beetle",
		"revision_timestamp": "2016-07-27T23:05:27.056513",
		"state": "active",
		"id": "37ff383e-e466-4efe-a6e6-67aa1bf55233"
	},
	{
		"vocabulary_id": null,
		"display_name": "bullsnake",
		"name": "bullsnake",
		"revision_timestamp": "2016-07-27T23:05:27.056513",
		"state": "active",
		"id": "039ec434-ce37-4947-ba3d-6f0fc279d7d1"
	},
	{
		"vocabulary_id": null,
		"display_name": "general-biology-at-risk-biota-te-species",
		"name": "general-biology-at-risk-biota-te-species",
		"revision_timestamp": "2016-07-27T23:05:27.056513",
		"state": "active",
		"id": "f0ef2fa4-3617-4be5-94ca-58164b07f45c"
	},
	{
		"vocabulary_id": null,
		"display_name": "giant-carrion-beetle",
		"name": "giant-carrion-beetle",
		"revision_timestamp": "2016-07-27T23:05:27.056513",
		"state": "active",
		"id": "78d032e1-1a6c-4c40-9cfc-2dc3be1a3cda"
	},
	{
		"vocabulary_id": null,
		"display_name": "gopher-snake",
		"name": "gopher-snake",
		"revision_timestamp": "2016-07-27T23:05:27.056513",
		"state": "active",
		"id": "29ccdeb8-c44f-4bce-822b-22f6aedaab8c"
	},
	{
		"vocabulary_id": null,
		"display_name": "habitat-loss",
		"name": "habitat-loss",
		"revision_timestamp": "2016-01-29T15:23:53.522464",
		"state": "active",
		"id": "87ac943a-f666-49c6-9c87-c0f32a8e5353"
	},
	{
		"vocabulary_id": null,
		"display_name": "nest-predator-management",
		"name": "nest-predator-management",
		"revision_timestamp": "2016-01-29T15:23:53.522464",
		"state": "active",
		"id": "e70d2568-b0fe-4249-8543-9a042fd3b75f"
	},
	{
		"vocabulary_id": null,
		"display_name": "nicrophorus-americanus",
		"name": "nicrophorus-americanus",
		"revision_timestamp": "2016-07-27T23:05:27.056513",
		"state": "active",
		"id": "d66ac8f0-9de4-4a54-9286-8107833c1403"
	},
	{
		"vocabulary_id": null,
		"display_name": "pituophis-catenifer",
		"name": "pituophis-catenifer",
		"revision_timestamp": "2016-07-27T23:05:27.056513",
		"state": "active",
		"id": "1823324e-9f24-4ad0-9c2d-0dce9b846823"
	},
	{
		"vocabulary_id": null,
		"display_name": "species-decline",
		"name": "species-decline",
		"revision_timestamp": "2016-01-29T15:23:53.522464",
		"state": "active",
		"id": "0219eded-8095-4d07-92ff-7076004b26dc"
	},
	{
		"vocabulary_id": null,
		"display_name": "species-recovery",
		"name": "species-recovery",
		"revision_timestamp": "2016-01-29T15:23:53.522464",
		"state": "active",
		"id": "437cd6f5-fa11-42b1-976b-5055b64319b5"
	}],
	"title": "Section 7 intra-service consultation, Fort Niobrara-Valentine National Wildlife Refuge Complex, bullsnake control [American burying beetle]",
	"tracking_summary": {
		"total": 5,
		"recent": 1
	},
	"groups": [],
	"relationships_as_subject": [],
	"revision_timestamp": "2016-11-16T19:48:02.953063",
	"name": "section-7-intra-service-consultation-fort-niobrara-valentine-national-wildlife-refuge-comp",
	"isopen": false,
	"url": null,
	"notes": "This biological opinion is provided in response to your request for an Intra-Service Section 7 consultation on a proposal to continue bullsnake (Pituophis catenifer) trapping activities on Fort Niobrara-Valentine National Wildlife Refuge (Valentine). The submitted Intra- Service Consultation Project Evaluation form concluded that the project \"may affect\" the federally listed endangered American burying beetle (Nicrophorus americanus). This opinion was prepared in accordance with Section 7 of the Endangered Species Act of 1973 and the Interagency Cooperation Regulations (50 CFR 402).  The final biological opinion is that the proposed continuation of bullsnake trapping at Valentine NWR, using funnel-type traps, is is not likely to jeopardize the continued existence of the American burying beetle.",
	"license_title": "License Not Specified",
	"extras": [{
		"key": "harvest_source_id",
		"value": "269d76fb-fa7e-49d2-a6bb-3a9e3f1bee70"
	},
	{
		"key": "issued",
		"value": "1993-10-01"
	},
	{
		"key": "resource-type",
		"value": "Dataset"
	},
	{
		"key": "references",
		"value": ["https:\/\/ecos.fws.gov\/ServCat\/Reference\/Profile\/55470"]
	},
	{
		"key": "source_hash",
		"value": "24bec1d3976e1fd6c016dae24ae96b06088c5938"
	},
	{
		"key": "accessLevel",
		"value": "public"
	},
	{
		"key": "theme",
		"value": ["Generic Document"]
	},
	{
		"key": "spatial",
		"value": "-100.736,42.40702,-100.3495,42.93301"
	},
	{
		"key": "catalog_conformsTo",
		"value": "https:\/\/project-open-data.cio.gov\/v1.1\/schema"
	},
	{
		"key": "catalog_@context",
		"value": "https:\/\/project-open-data.cio.gov\/v1.1\/schema\/catalog.jsonld"
	},
	{
		"key": "catalog_describedBy",
		"value": "https:\/\/project-open-data.cio.gov\/v1.1\/schema\/catalog.json"
	},
	{
		"key": "harvest_source_title",
		"value": "fwsjson"
	},
	{
		"key": "source_schema_version",
		"value": "1.1"
	},
	{
		"key": "programCode",
		"value": ["010:094",
		"010:028"]
	},
	{
		"key": "bureauCode",
		"value": ["010:18"]
	},
	{
		"key": "landingPage",
		"value": "https:\/\/ecos.fws.gov\/ServCat\/Reference\/Profile\/55470"
	},
	{
		"key": "harvest_object_id",
		"value": "172c145e-6191-4012-9d95-5b21ba765d13"
	},
	{
		"key": "publisher",
		"value": "Fish and Wildlife Service"
	},
	{
		"key": "modified",
		"value": "1993-10-01"
	},
	{
		"key": "source_datajson_identifier",
		"value": true
	},
	{
		"key": "catalog_@id",
		"value": "C:\\Program Files (x86)\\FWS\\DataStore\\Application\\OpenData\\FWS_ServCat_v1_1.json"
	},
	{
		"key": "dataQuality",
		"value": true
	},
	{
		"key": "identifier",
		"value": "FWS_ServCat_55470"
	},
	{
		"state": "active",
		"key": "harvest_object_id",
		"value": "172c145e-6191-4012-9d95-5b21ba765d13"
	},
	{
		"state": "active",
		"key": "harvest_source_id",
		"value": "269d76fb-fa7e-49d2-a6bb-3a9e3f1bee70"
	},
	{
		"state": "active",
		"key": "harvest_source_title",
		"value": "fwsjson"
	}],
	"organization": {
		"description": "",
		"created": "2013-03-14T03:44:48.890979",
		"title": "US Fish and Wildlife Service, Department of the Interior",
		"name": "fws-gov",
		"revision_timestamp": "2013-08-10T21:40:21.503248",
		"is_organization": true,
		"state": "active",
		"image_url": "http:\/\/upload.wikimedia.org\/wikipedia\/commons\/0\/0c\/US-FishAndWildlifeService-Logo.svg",
		"revision_id": "353573b3-02ba-4e95-a876-828e8972ac08",
		"type": "organization",
		"id": "4d7ad1cd-3641-420b-8116-e4082f49cd44",
		"approval_status": "approved"
	},
	"revision_id": "6380dd10-ef46-4348-930d-f92021c9dc21"
}