{
	"owner_org": "735d0118-b2a7-4246-a0e3-608b0fa8d1ec",
	"maintainer": "KC Hallett",
	"relationships_as_object": [],
	"private": false,
	"maintainer_email": "kathleen.hallett@nrel.gov",
	"num_tags": 5,
	"id": "7f8ed7aa-77ad-4d6a-9654-c95e4a4c6651",
	"metadata_created": "2015-02-23T20:22:45.972525",
	"metadata_modified": "2015-03-13T20:44:27.381966",
	"author": null,
	"author_email": null,
	"state": "active",
	"version": null,
	"license_id": null,
	"type": "dataset",
	"resources": [{
		"resource_group_id": "dda56762-328a-4042-a2c9-da93221be9f8",
		"cache_last_updated": null,
		"revision_timestamp": "2015-02-23T20:22:45.972525",
		"webstore_last_updated": null,
		"id": "94db5f04-e9d9-4b96-af72-a4548f0e2294",
		"size": null,
		"state": "active",
		"hash": "",
		"description": "Energy intensity data and documentation published by the U.S. DOE's office of Energy Efficiency and Renewable Energy (EERE).",
		"format": "XLS",
		"tracking_summary": {
			"total": 12,
			"recent": 1
		},
		"mimetype_inner": null,
		"mimetype": "application\/vnd.ms-excel",
		"cache_url": null,
		"name": "industrialindicators.xls",
		"created": "2015-02-23T15:22:46.205572",
		"url": "http:\/\/en.openei.org\/doe-opendata\/dataset\/f6c9151f-3488-452e-a898-f4f607a025e8\/resource\/c19dba77-47f4-47f3-b2a0-e20c3297f8b3\/download\/industrialindicators.xls",
		"webstore_url": null,
		"last_modified": null,
		"position": 0,
		"revision_id": "46b4e3fe-2405-4c27-94f3-21a088a953d1",
		"resource_type": null
	}],
	"num_resources": 1,
	"tags": [{
		"vocabulary_id": null,
		"display_name": "energy-consumption",
		"name": "energy-consumption",
		"revision_timestamp": "2015-02-23T20:22:45.972525",
		"state": "active",
		"id": "08444987-9f5a-4e3d-83a2-a50094a66c43"
	},
	{
		"vocabulary_id": null,
		"display_name": "energy-intensity",
		"name": "energy-intensity",
		"revision_timestamp": "2015-02-23T20:22:45.972525",
		"state": "active",
		"id": "002c66d8-ab1d-4e2f-86b1-4b034629c30b"
	},
	{
		"vocabulary_id": null,
		"display_name": "fossil-fuels",
		"name": "fossil-fuels",
		"revision_timestamp": "2015-02-23T20:22:45.972525",
		"state": "active",
		"id": "2143e00f-65c1-4818-b8e1-f334f702352e"
	},
	{
		"vocabulary_id": null,
		"display_name": "industrial-sector",
		"name": "industrial-sector",
		"revision_timestamp": "2015-02-23T20:22:45.972525",
		"state": "active",
		"id": "0fd461e9-a5c5-4c3a-a1f8-3678605963f4"
	},
	{
		"vocabulary_id": null,
		"display_name": "renewable-energy",
		"name": "renewable-energy",
		"revision_timestamp": "2015-02-23T20:22:45.972525",
		"state": "active",
		"id": "20119afd-da47-48f2-9fde-640d3678862f"
	}],
	"title": "Energy Intensity Indicators in the U.S.: Industrial Sector (1949 - 2004)",
	"tracking_summary": {
		"total": 10,
		"recent": 2
	},
	"groups": [],
	"relationships_as_subject": [],
	"revision_timestamp": "2015-02-23T20:22:45.972525",
	"name": "energy-intensity-indicators-in-the-u-s-industrial-sector-1949-2004-e63d2",
	"isopen": true,
	"url": null,
	"notes": "Energy intensity data and documentation published by the U.S. DOE's office of Energy Efficiency and Renewable Energy (EERE). Energy intensity is defined as: amount of energy used in producing a given level of output or activity; expressed as energy per unit of output. This is the energy intensity of the the industrial sector, which is an end-use that consists of all facilities and equipment used for producing, processing, or assembling goods. It is comprised of: manufacturing, agriculture, forestry, fisheries, mining and construction. Data is available for the period 1949 - 2004.",
	"license_title": "Other License Specified",
	"extras": [{
		"key": "accessURL",
		"value": "http:\/\/en.openei.org\/doe-opendata\/dataset\/f6c9151f-3488-452e-a898-f4f607a025e8\/resource\/c19dba77-47f4-47f3-b2a0-e20c3297f8b3\/download\/industrialindicators.xls"
	},
	{
		"key": "publisher",
		"value": "Office of Energy Efficiency & Renewable Energy (EERE)"
	},
	{
		"key": "accessLevel",
		"value": "public"
	},
	{
		"key": "license",
		"value": "http:\/\/www.opendefinition.org\/licenses\/odc-by"
	},
	{
		"key": "harvest_source_id",
		"value": "8d4de31c-979c-4b50-be6b-ea3c72453ff6"
	},
	{
		"key": "catalog_@context",
		"value": "https:\/\/project-open-data.cio.gov\/v1.1\/schema\/catalog.jsonld"
	},
	{
		"key": "format",
		"value": "application\/vnd.ms-excel"
	},
	{
		"key": "resource-type",
		"value": "Dataset"
	},
	{
		"key": "modified",
		"value": "2014-11-25T18:16:06Z"
	},
	{
		"key": "harvest_source_title",
		"value": "Energy JSON"
	},
	{
		"key": "source_schema_version",
		"value": "1.1"
	},
	{
		"key": "source_datajson_identifier",
		"value": true
	},
	{
		"key": "programCode",
		"value": ["019:000"]
	},
	{
		"key": "identifier",
		"value": "http:\/\/en.openei.org\/doe-opendata\/dataset\/f6c9151f-3488-452e-a898-f4f607a025e8"
	},
	{
		"key": "bureauCode",
		"value": ["019:20"]
	},
	{
		"key": "dataQuality",
		"value": true
	},
	{
		"key": "landingPage",
		"value": "http:\/\/www1.eere.energy.gov\/ba\/pba\/intensityindicators\/trend_data.html"
	},
	{
		"key": "harvest_object_id",
		"value": "08a63522-60f3-441e-9eab-2fa28fea0c0b"
	},
	{
		"key": "source_hash",
		"value": "195668a6dffac81a4ef5811c87d4c45d96d028ae"
	},
	{
		"key": "catalog_conformsTo",
		"value": "https:\/\/project-open-data.cio.gov\/v1.1\/schema"
	},
	{
		"key": "catalog_describedBy",
		"value": "https:\/\/project-open-data.cio.gov\/v1.1\/schema\/catalog.json"
	},
	{
		"state": "active",
		"key": "harvest_object_id",
		"value": "08a63522-60f3-441e-9eab-2fa28fea0c0b"
	},
	{
		"state": "active",
		"key": "harvest_source_id",
		"value": "8d4de31c-979c-4b50-be6b-ea3c72453ff6"
	},
	{
		"state": "active",
		"key": "harvest_source_title",
		"value": "Energy JSON"
	}],
	"organization": {
		"description": "",
		"created": "2013-05-18T11:31:21.471948",
		"title": "Department of Energy",
		"name": "doe-gov",
		"revision_timestamp": "2013-05-31T20:48:37.771905",
		"is_organization": true,
		"state": "active",
		"image_url": "http:\/\/energy.gov\/sites\/prod\/files\/styles\/imagelink\/public\/DoE-Logo.jpeg",
		"revision_id": "14e1d3c1-4cc7-460c-bf1c-b10e3429b4b0",
		"type": "organization",
		"id": "735d0118-b2a7-4246-a0e3-608b0fa8d1ec",
		"approval_status": "approved"
	},
	"revision_id": "46b4e3fe-2405-4c27-94f3-21a088a953d1"
}